interposition/__init__.py
interposition/_version.py
interposition/errors.py
interposition/models.py
interposition/py.typed
interposition/services.py
interposition/stores.py
interposition-0.3.0.dist-info/licenses/LICENSE
interposition-0.3.0.dist-info/METADATA
interposition-0.3.0.dist-info/WHEEL
interposition-0.3.0.dist-info/top_level.txt
interposition-0.3.0.dist-info/RECORD
