Metadata-Version: 2.4
Name: interposition
Version: 0.3.0
Summary: Protocol-agnostic interaction interposition with lifecycle hooks for record, replay, and control.
Author: osoken
License-Expression: MIT
Project-URL: Homepage, https://github.com/osoekawaitlab/interposition
Project-URL: Repository, https://github.com/osoekawaitlab/interposition
Classifier: Development Status :: 4 - Beta
Classifier: Intended Audience :: Developers
Classifier: Operating System :: POSIX
Classifier: Programming Language :: Python :: 3 :: Only
Classifier: Programming Language :: Python :: 3.10
Classifier: Programming Language :: Python :: 3.11
Classifier: Programming Language :: Python :: 3.12
Classifier: Programming Language :: Python :: 3.13
Classifier: Typing :: Typed
Requires-Python: >=3.10
License-File: LICENSE
Requires-Dist: pydantic<3.0,>=2.0
Dynamic: license-file
